LICENSE
setup.py
nbeats_lightning/__init__.py
nbeats_lightning/loaders.py
nbeats_lightning/losses.py
nbeats_lightning/nbeats.py
nbeats_lightning/utils.py
nbeats_lightning.egg-info/PKG-INFO
nbeats_lightning.egg-info/SOURCES.txt
nbeats_lightning.egg-info/dependency_links.txt
nbeats_lightning.egg-info/not-zip-safe
nbeats_lightning.egg-info/requires.txt
nbeats_lightning.egg-info/top_level.txt