Metadata-Version: 2.1
Name: nbeats-lightning
Version: 0.1.0
Summary: A Pytorch Lignthing implementation of N-BEATS.
Home-page: https://github.com/realdanielbyrne/N-BEATS-Lightning
Author: Daniel Byrne
Author-email: realdanielbyrne@icloud.com
Keywords: time series forecasting
Classifier: Intended Audience :: Science/Research
Classifier: Intended Audience :: Developers
Classifier: Programming Language :: Python
Classifier: Topic :: Software Development
Classifier: Topic :: Scientific/Engineering
Classifier: Operating System :: Microsoft :: Windows
Classifier: Operating System :: POSIX
Classifier: Operating System :: Unix
Classifier: Operating System :: MacOS
Classifier: Programming Language :: Python :: 3
Classifier: Programming Language :: Python :: 3.9
Classifier: Programming Language :: Python :: 3.10
Classifier: Programming Language :: Python :: Implementation :: PyPy
Requires-Python: >=3.9
License-File: LICENSE
